Workbook

Sheet 说明
B2: 山海企划 · 义卖系统 BOM 与预算
B4: 用途：采购与征借跟踪。配套《山海企划-项目文档.docx》第 11 章与 docs/10-BOM物料清单与预算.md。
B6: 工作表结构：
B7: 1) BOM明细 —— 36 项物料，小计为公式（改数量/单价自动重算）；「征借优先=是」的行在征借两列按 0 计提。
B8: 2) 预算汇总 —— 按类别 SUMIF 汇总 + 备用金率（黄色输入格，可改）+ 合计，双档：全新采购 / 征借优先。
B9: 3) 服务器配置单 —— 三台服务器的规格、端口、数据与备份策略。
B10: 4) 采购跟踪 —— 按 W1–W8 的采购/验收动作，状态下拉可选。
B12: 颜色约定：
B13: 表头深蓝底白字；黄色底=可修改的输入格；其余数值均为公式，请勿直接改写。
B15: 提醒：单价为 2026 年电商/租赁市场参考区间；G 类纪念品（约 3,000 份 × 2–5 元）由业务口另行立项，不计入系统侧合计。
B16: 密钥/激活码等无形资产不在 BOM 内，见《部署与现场运维手册》密钥包条目。

Sheet BOM明细
A1: 编号 | B1: 类别 | C1: 物料名称 | D1: 规格说明 | E1: 数量 | F1: 单位 | G1: 单价低(¥) | H1: 单价高(¥) | I1: 全新·小计低 | J1: 全新·小计高 | K1: 征借·小计低 | L1: 征借·小计高 | M1: 征借优先 | N1: 备注
A2: A1 | B2: A 云资源与计算 | C2: 云服务器·前端聚合（F1+F2） | D2: 华为云 ECS 16C32G，系统盘+数据盘 500G，EIP 带宽峰值 500M（按流量计费）；TLS 网关 SNI 分流 api/static；shs-catalog + shs-trade 双进程 | E2: 1 | F2: 台 | G2: 1300 | H2: 3200 | I2: =E2*G2 | J2: =E2*H2 | K2: =IF($M2="是",0,I2) | L2: =IF($M2="是",0,J2) | M2: 否 | N2: 包月 1–2 个月，活动后释放/降配；4C8G 即满足论证容量，16C32G 为余量/复用选择
A3: A2 | B3: A 云资源与计算 | C3: 云服务器·BE（账本） | D3: 华为云 ECS 2C4G，数据盘 40G，公网 IP；shs-core | E3: 1 | F3: 台 | G3: 150 | H3: 400 | I3: =E3*G3 | J3: =E3*H3 | K3: =IF($M3="是",0,I3) | L3: =IF($M3="是",0,J3) | M3: 否 | N3: 与聚合机分离保留故障域
A4: A3 | B4: A 云资源与计算 | C4: CDN 流量包 | D4: ≥100GB；图片/静态边缘分流≈90% 读流量；/api/* 一律不缓存 | E4: 1 | F4: 个 | G4: 20 | H4: 60 | I4: =E4*G4 | J4: =E4*H4 | K4: =IF($M4="是",0,I4) | L4: =IF($M4="是",0,J4) | M4: 否
A5: A4 | B5: A 云资源与计算 | C5: 域名 + SSL 证书 | D5: 备案域名一年 + 云免费证书 ×3（edge/be/static） | E5: 1 | F5: 项 | G5: 50 | H5: 100 | I5: =E5*G5 | J5: =E5*H5 | K5: =IF($M5="是",0,I5) | L5: =IF($M5="是",0,J5) | M5: 否 | N5: ★ 备案周期 1–3 周，W1 立即启动
A6: A5 | B6: A 云资源与计算 | C6: 对象存储（可选） | D6: 50GB 备份桶（数据三备份介质之一） | E6: 1 | F6: 个 | G6: 0 | H6: 30 | I6: =E6*G6 | J6: =E6*H6 | K6: =IF($M6="是",0,I6) | L6: =IF($M6="是",0,J6) | M6: 否 | N6: 可用云盘快照替代
A7: A6 | B7: A 云资源与计算 | C7: 运维笔记本 | D7: 现场管理/监控大屏/离线备份，SSH 密钥 | E7: 1 | F7: 台 | G7: 0 | H7: 0 | I7: =E7*G7 | J7: =E7*H7 | K7: =IF($M7="是",0,I7) | L7: =IF($M7="是",0,J7) | M7: 是 | N7: 仅征借
A8: A7 | B8: A 云资源与计算 | C8: 备份 U 盘 | D8: 64G USB3 ×2（账本离线双介质，活动结束当场带离） | E8: 2 | F8: 个 | G8: 35 | H8: 60 | I8: =E8*G8 | J8: =E8*H8 | K8: =IF($M8="是",0,I8) | L8: =IF($M8="是",0,J8) | M8: 否 | N8: ★ 安全库存必须
A9: A8 | B9: A 云资源与计算 | C9: 入口大屏动态码终端 | D9: 平板/笔记本/一体机，横屏 ≥10 英寸（每 2s 刷新入场码） | E9: 1 | F9: 台 | G9: 800 | H9: 1200 | I9: =E9*G9 | J9: =E9*H9 | K9: =IF($M9="是",0,I9) | L9: =IF($M9="是",0,J9) | M9: 是 | N9: 配支架
A10: A9 | B10: A 云资源与计算 | C10: 大屏支架/桌架 | D10: 落地或桌面支架，顾客扫码高度约 1.2m | E10: 1 | F10: 个 | G10: 60 | H10: 150 | I10: =E10*G10 | J10: =E10*H10 | K10: =IF($M10="是",0,I10) | L10: =IF($M10="是",0,J10) | M10: 否
A11: B1 | B11: B 网络设备 | C11: QCI6 CPE（主） | D11: 5G/4G CPE，带千兆 LAN + Wi-Fi，现场统一出口 | E11: 1 | F11: 台 | G11: 400 | H11: 700 | I11: =E11*G11 | J11: =E11*H11 | K11: =IF($M11="是",0,I11) | L11: =IF($M11="是",0,J11) | M11: 否 | N11: 出口仅 API 流量（CDN 已卸载图片）
A12: B2 | B12: B 网络设备 | C12: QCI6 CPE（备） | D12: 同上，冷备换插即用 ≤5min | E12: 1 | F12: 台 | G12: 400 | H12: 700 | I12: =E12*G12 | J12: =E12*H12 | K12: =IF($M12="是",0,I12) | L12: =IF($M12="是",0,J12) | M12: 否 | N12: 异网 SIM
A13: B3 | B13: B 网络设备 | C13: 数据 SIM 卡 | D13: 流量包 ≥20G/卡，分属两家运营商 | E13: 2 | F13: 张 | G13: 0 | H13: 0 | I13: =E13*G13 | J13: =E13*H13 | K13: =IF($M13="是",0,I13) | L13: =IF($M13="是",0,J13) | M13: 否 | N13: 已办理√（存量）
A14: B4 | B14: B 网络设备 | C14: 核心路由器 | D14: 千兆，可刷 OpenWrt（防火墙/静态路由/DNS） | E14: 1 | F14: 台 | G14: 150 | H14: 300 | I14: =E14*G14 | J14: =E14*H14 | K14: =IF($M14="是",0,I14) | L14: =IF($M14="是",0,J14) | M14: 是 | N14: 或 CPE 路由模式直挂
A15: B5 | B15: B 网络设备 | C15: 交换机 SW1 | D15: 8 口千兆非网管（运维本/大屏/打印机） | E15: 1 | F15: 台 | G15: 100 | H15: 180 | I15: =E15*G15 | J15: =E15*H15 | K15: =IF($M15="是",0,I15) | L15: =IF($M15="是",0,J15) | M15: 否
A16: B6 | B16: B 网络设备 | C16: PoE 交换机 SW2 | D16: 8 口千兆 PoE（AP 供电） | E16: 1 | F16: 台 | G16: 300 | H16: 500 | I16: =E16*G16 | J16: =E16*H16 | K16: =IF($M16="是",0,I16) | L16: =IF($M16="是",0,J16) | M16: 否 | N16: 或 PoE 注入器 ×3 可省约 200
A17: B7 | B17: B 网络设备 | C17: Wi-Fi 6 AP | D17: 双频 AX3000 级，多 SSID（入口/队伍、提货/纪念、浏览/机动） | E17: 3 | F17: 台 | G17: 250 | H17: 450 | I17: =E17*G17 | J17: =E17*H17 | K17: =IF($M17="是",0,I17) | L17: =IF($M17="是",0,J17) | M17: 否 | N17: 单 AP 建议 ≤80 终端
A18: B8 | B18: B 网络设备 | C18: 网线与配件 | D18: Cat6 成品线 1m/3m/10m 合计 12 根 + 水晶头工具包（含备线 4 根） | E18: 1 | F18: 套 | G18: 120 | H18: 200 | I18: =E18*G18 | J18: =E18*H18 | K18: =IF($M18="是",0,I18) | L18: =IF($M18="是",0,J18) | M18: 否 | N18: ★
A19: B9 | B19: B 网络设备 | C19: 测线仪/寻线器 | D19: 简易网络测线仪 | E19: 1 | F19: 个 | G19: 30 | H19: 80 | I19: =E19*G19 | J19: =E19*H19 | K19: =IF($M19="是",0,I19) | L19: =IF($M19="是",0,J19) | M19: 否
A20: C1 | B20: C 员工终端与外设 | C20: 员工手机 | D20: 安卓 ≥8.0、支持 BLE（个人机征用优先），分配见部署手册 | E20: 10 | F20: 台 | G20: 600 | H20: 1200 | I20: =E20*G20 | J20: =E20*H20 | K20: =IF($M20="是",0,I20) | L20: =IF($M20="是",0,J20) | M20: 是 | N20: 入口2/队列3/配货2/提货2/纪念1
A21: C2 | B21: C 员工终端与外设 | C21: 管理平板 | D21: 安卓平板 ≥10 英寸（ADMIN 大屏+走动指挥） | E21: 1 | F21: 台 | G21: 900 | H21: 1500 | I21: =E21*G21 | J21: =E21*H21 | K21: =IF($M21="是",0,I21) | L21: =IF($M21="是",0,J21) | M21: 是
A22: C3 | B22: C 员工终端与外设 | C22: 热敏小票打印机 | D22: 58mm 蓝牙（佳博/芯烨类），ESC/POS；配货区×2+提货区热备×1 | E22: 3 | F22: 台 | G22: 180 | H22: 320 | I22: =E22*G22 | J22: =E22*H22 | K22: =IF($M22="是",0,I22) | L22: =IF($M22="是",0,J22) | M22: 否 | N22: ★ 最高频故障点
A23: C4 | B23: C 员工终端与外设 | C23: 热敏纸卷 | D23: 57×30mm（约 250 张/卷）；按峰值 3000 单×2 联冗余 | E23: 60 | F23: 卷 | G23: 1.5 | H23: 2.5 | I23: =E23*G23 | J23: =E23*H23 | K23: =IF($M23="是",0,I23) | L23: =IF($M23="是",0,J23) | M23: 否 | N23: ★
A24: C5 | B24: C 员工终端与外设 | C24: 打印机电源/线材 | D24: 原配 DC 线 + USB 兜底线 | E24: 3 | F24: 套 | G24: 0 | H24: 0 | I24: =E24*G24 | J24: =E24*H24 | K24: =IF($M24="是",0,I24) | L24: =IF($M24="是",0,J24) | M24: 否 | N24: 随机附带
A25: D1 | B25: D 电源与续航 | C25: 小型 UPS（可选） | D25: 现场网络设备（AP/交换机/CPE）断电续航 ≥30min | E25: 1 | F25: 台 | G25: 200 | H25: 350 | I25: =E25*G25 | J25: =E25*H25 | K25: =IF($M25="是",0,I25) | L25: =IF($M25="是",0,J25) | M25: 否 | N25: 服务器在云端，无需大 UPS
A26: D2 | B26: D 电源与续航 | C26: 大功率充电宝 | D26: 20,000mAh PD 30W+，员工终端全岗位覆盖 | E26: 6 | F26: 个 | G26: 100 | H26: 180 | I26: =E26*G26 | J26: =E26*H26 | K26: =IF($M26="是",0,I26) | L26: =IF($M26="是",0,J26) | M26: 否 | N26: ★
A27: D3 | B27: D 电源与续航 | C27: 多口充电器 | D27: 65W GaN 3 口，指挥台集中补电 | E27: 4 | F27: 个 | G27: 80 | H27: 140 | I27: =E27*G27 | J27: =E27*H27 | K27: =IF($M27="是",0,I27) | L27: =IF($M27="是",0,J27) | M27: 否
A28: D4 | B28: D 电源与续航 | C28: 插线板 | D28: 6 位 ×1.8m 安全长款，各工位 | E28: 6 | F28: 个 | G28: 30 | H28: 60 | I28: =E28*G28 | J28: =E28*H28 | K28: =IF($M28="是",0,I28) | L28: =IF($M28="是",0,J28) | M28: 否
A29: D5 | B29: D 电源与续航 | C29: 手机备用数据线 | D29: USB-C/Lightning 混装（易耗必损件） | E29: 10 | F29: 根 | G29: 10 | H29: 25 | I29: =E29*G29 | J29: =E29*H29 | K29: =IF($M29="是",0,I29) | L29: =IF($M29="是",0,J29) | M29: 否 | N29: ★
A30: E1 | B30: E 通信与现场物料 | C30: 对讲机 | D30: 民用 409MHz 免执照（网络降级时的沟通保障） | E30: 6 | F30: 台 | G30: 60 | H30: 120 | I30: =E30*G30 | J30: =E30*H30 | K30: =IF($M30="是",0,I30) | L30: =IF($M30="是",0,J30) | M30: 否
A31: E2 | B31: E 通信与现场物料 | C31: 指引物料 | D31: 入口二维码立牌、流程指引海报 ×6、隐私公示牌（含数据30天销毁声明） | E31: 1 | F31: 套 | G31: 200 | H31: 400 | I31: =E31*G31 | J31: =E31*H31 | K31: =IF($M31="是",0,I31) | L31: =IF($M31="是",0,J31) | M31: 否
A32: E3 | B32: E 通信与现场物料 | C32: 桌牌/工牌 | D32: 分区胸牌：ENTRY蓝/QUEUE绿/PICKUP橙/SOUVENIR紫/ADMIN红 | E32: 12 | F32: 个 | G32: 5 | H32: 10 | I32: =E32*G32 | J32: =E32*H32 | K32: =IF($M32="是",0,I32) | L32: =IF($M32="是",0,J32) | M32: 否
A33: E4 | B33: E 通信与现场物料 | C33: 登记本+文具 | D33: 半离线应急登记本 ×3、笔、垫板（RB-04 兜底） | E33: 1 | F33: 套 | G33: 30 | H33: 60 | I33: =E33*G33 | J33: =E33*H33 | K33: =IF($M33="是",0,I33) | L33: =IF($M33="是",0,J33) | M33: 否
A34: E5 | B34: E 通信与现场物料 | C34: 警示带/围栏线 | D34: 排队动线管理 | E34: 1 | F34: 套 | G34: 50 | H34: 100 | I34: =E34*G34 | J34: =E34*H34 | K34: =IF($M34="是",0,I34) | L34: =IF($M34="是",0,J34) | M34: 否
A35: E6 | B35: E 通信与现场物料 | C35: 工具包 | D35: 螺丝刀/扎带/绝缘胶带/备用水晶头 | E35: 1 | F35: 套 | G35: 80 | H35: 150 | I35: =E35*G35 | J35: =E35*H35 | K35: =IF($M35="是",0,I35) | L35: =IF($M35="是",0,J35) | M35: 否
A36: F1 | B36: F 软件与账号 | C36: 微信小程序账号认证费 | D36: 学生组织可挂学校主体复用认证则为 0 | E36: 1 | F36: 项 | G36: 0 | H36: 300 | I36: =E36*G36 | J36: =E36*H36 | K36: =IF($M36="是",0,I36) | L36: =IF($M36="是",0,J36) | M36: 否
A37: F2 | B37: F 软件与账号 | C37: 云上软件/证书 | D37: 全自研 Rust + 云免费证书（Debian 开源） | E37: 1 | F37: 项 | G37: 0 | H37: 0 | I37: =E37*G37 | J37: =E37*H37 | K37: =IF($M37="是",0,I37) | L37: =IF($M37="是",0,J37) | M37: 否 | N37: 0 元
D38: 合计（A–F 类） | I38: =SUM(I2:I37) | J38: =SUM(J2:J37) | K38: =SUM(K2:K37) | L38: =SUM(L2:L37)

Sheet 预算汇总
A1: 山海企划 · 预算汇总（币种 CNY）
A3: 类别 | B3: 全新采购·低 | C3: 全新采购·高 | D3: 征借优先·低 | E3: 征借优先·高
A4: A 云资源与计算 | B4: =SUMIF('BOM明细'!$B:$B,$A4,'BOM明细'!I:I) | C4: =SUMIF('BOM明细'!$B:$B,$A4,'BOM明细'!J:J) | D4: =SUMIF('BOM明细'!$B:$B,$A4,'BOM明细'!K:K) | E4: =SUMIF('BOM明细'!$B:$B,$A4,'BOM明细'!L:L)
A5: B 网络设备 | B5: =SUMIF('BOM明细'!$B:$B,$A5,'BOM明细'!I:I) | C5: =SUMIF('BOM明细'!$B:$B,$A5,'BOM明细'!J:J) | D5: =SUMIF('BOM明细'!$B:$B,$A5,'BOM明细'!K:K) | E5: =SUMIF('BOM明细'!$B:$B,$A5,'BOM明细'!L:L)
A6: C 员工终端与外设 | B6: =SUMIF('BOM明细'!$B:$B,$A6,'BOM明细'!I:I) | C6: =SUMIF('BOM明细'!$B:$B,$A6,'BOM明细'!J:J) | D6: =SUMIF('BOM明细'!$B:$B,$A6,'BOM明细'!K:K) | E6: =SUMIF('BOM明细'!$B:$B,$A6,'BOM明细'!L:L)
A7: D 电源与续航 | B7: =SUMIF('BOM明细'!$B:$B,$A7,'BOM明细'!I:I) | C7: =SUMIF('BOM明细'!$B:$B,$A7,'BOM明细'!J:J) | D7: =SUMIF('BOM明细'!$B:$B,$A7,'BOM明细'!K:K) | E7: =SUMIF('BOM明细'!$B:$B,$A7,'BOM明细'!L:L)
A8: E 通信与现场物料 | B8: =SUMIF('BOM明细'!$B:$B,$A8,'BOM明细'!I:I) | C8: =SUMIF('BOM明细'!$B:$B,$A8,'BOM明细'!J:J) | D8: =SUMIF('BOM明细'!$B:$B,$A8,'BOM明细'!K:K) | E8: =SUMIF('BOM明细'!$B:$B,$A8,'BOM明细'!L:L)
A9: F 软件与账号 | B9: =SUMIF('BOM明细'!$B:$B,$A9,'BOM明细'!I:I) | C9: =SUMIF('BOM明细'!$B:$B,$A9,'BOM明细'!J:J) | D9: =SUMIF('BOM明细'!$B:$B,$A9,'BOM明细'!K:K) | E9: =SUMIF('BOM明细'!$B:$B,$A9,'BOM明细'!L:L)
A10: 小计（不含 G 纪念品） | B10: =SUM(B4:B9) | C10: =SUM(C4:C9) | D10: =SUM(D4:D9) | E10: =SUM(E4:E9)
A11: 备用金率（可修改） | B11: 0.1
A12: 备用金 | B12: =ROUND(B10*$B$11,0) | C12: =ROUND(C10*$B$11,0) | D12: =ROUND(D10*$B$11,0) | E12: =ROUND(E10*$B$11,0)
A13: 系统侧合计 | B13: =B10+B12 | C13: =C10+C12 | D13: =D10+D12 | E13: =E10+E12
A15: 注：G 类纪念品（约 3,000 份 × 2–5 元 = 6,000–15,000 元）由业务口另行立项，不计入上表。
A16: 征借优先档：A/B/C 类中「征借优先=是」的物料按 0 计提（BOM明细 K/L 列公式自动处理）。

Sheet 服务器配置单
A1: 项目 | B1: 前端聚合机（F1+F2） | C1: BE 账本机 | D1: —
A2: 主机名 / 域名 | B2: edge / edge.<备案域名>（static 回源同机） | C2: be / be.<备案域名> | D2: —
A3: 云规格 | B3: 华为云 ECS 16C32G，盘 500G，EIP 带宽峰值 500M（按流量计费） | C3: 华为云 ECS 2C4G，数据盘 40G | D3: —
A4: 操作系统 | B4: Debian 12 / Ubuntu 22.04 + systemd | C4: 同左 | D4: —
A5: 进程 | B5: Nginx/Caddy 网关(SNI: api/static) + shs-catalog + shs-trade 双进程 | C5: shs-core（单二进制） | D5: —
A6: 监听 | B6: 443 → 127.0.0.1:8443(catalog)/8444(trade) | C6: 443 HTTPS/WSS | D6: —
A7: 数据 | B7: catalog.db、registry.db、outbox/*.wal、inventory.snapshot、/srv/static/ | C7: core.db（订单/员工/纪念品/审计） | D7: —
A8: 时钟 | B8: 云镜像默认 chrony → 云厂商内网 NTP | C8: 同左 | D8: —
A9: 备份策略 | B9: 云盘快照；活动结束归档双介质 | C9: 每 30min VACUUM INTO + 云快照 + U 盘离线副本 | D9: —
A10: 安全组 | B10: 公网仅 443；SSH 22 仅运维出口 IP + 密钥 | C10: 同左 | D10: —
A11: 关键调优参数 | B11: batch_max=50；batch_interval=1s；退避 1/2/4/5/5s；图片 webp ≤200KB；匿名限流 30 req/min | C11: 心跳 15s；45s 判离线改派 | D11: —
A12: 故障处置 | B12: catalog/trade 进程独立重启；整机故障走云镜像+数据盘 3min 重建 | C12: 重启 ≤30s，WAL/账本无损 | D12: —

Sheet 采购跟踪
A1: 周次 | B1: 动作 | C1: 负责人 | D1: 状态 | E1: 完成日期 | F1: 备注
A2: W1 | B2: 域名/备案立即启动（1–3 周）；云 ECS×2 开通初始化；CDN 开通与缓存规则验证 | C2: 成员A/B | D2: 进行中
A3: W1 | B3: 征借申请发出（学校资产/社团/个人）；全新采购项比价下单 | C3: 成员B | D3: 待办
A4: W1 | B4: SIM 核对（已办理√）：确认两卡流量余额 ≥20G、分属两家运营商 | C4: 成员B | D4: 已完成
A5: W2–W3 | B5: 到货验收（对照 BOM 逐项打勾） | C5: 成员B | D5: 待办
A6: W4–W5 | B6: 打印机机型兼容验证（C3 到货即测）；AP 实地试装；云上压测（含公网链路） | C6: 成员B | D6: 待办
A7: W6 | B7: 全部物料齐套核查；缺项启动替代方案；云资源费用复核 | C7: 成员A/B | D7: 待办
A8: W7 | B8: 彩排全要素使用；耗材按彩排消耗补货 | C8: 成员A/B | D8: 待办
A9: W8 | B9: 装箱清单（箱号-物料-数量-负责人）随设备运输 | C9: 成员B | D9: 待办
A10: W8+ | B10: ECS 制作最终快照后释放/降配；CDN 停用；设备归还销账；密钥包销毁登记 | C10: 成员B | D10: 待办 | E10: 活动结束当日
